{"stats":{"minecraft:custom":{"minecraft:jump":51,"minecraft:time_since_rest":3310,"minecraft:damage_dealt":160,"minecraft:damage_taken":1380,"minecraft:leave_game":7,"minecraft:crouch_one_cm":208,"minecraft:time_since_death":3279,"minecraft:play_time":29052,"minecraft:sprint_one_cm":1231,"minecraft:walk_one_cm":11509,"minecraft:deaths":4,"minecraft:total_world_time":29153,"minecraft:sneak_time":136,"minecraft:mob_kills":8,"minecraft:fall_one_cm":5797,"minecraft:fly_one_cm":81224},"minecraft:killed_by":{"minecraft:slime":2,"minecraft:creeper":1},"minecraft:killed":{"minecraft:slime":6},"minecraft:picked_up":{"minecraft:slime_ball":2}},"DataVersion":3120}